apexmf/__init__.py
apexmf/apexmf_pst_par.py
apexmf/apexmf_pst_stats.py
apexmf/apexmf_pst_utils.py
apexmf/apexmf_pst_viz.py
apexmf/apexmf_scenario_utils.py
apexmf/apexmf_utils.py
apexmf/forward_run.py
apexmf/forward_run_gns.py
apexmf/forward_run_tmp.py
apexmf/salt_forward_run.py
apexmf/swat_par_chg_run.py
apexmf/utils.py
apexmf/version.py
apexmf/opt_files/amrs_rel230127.exe
apexmf/opt_files/apex.parm.xlsx
apexmf/opt_files/beopest64.exe
apexmf/opt_files/crop.parm
apexmf/opt_files/i64pest.exe
apexmf/opt_files/i64pwtadj1.exe
apexmf/salt/__init__.py
apexmf/salt/analyzer.py
apexmf/salt/salt_handler.py
apexmf-0.4.0.dist-info/LICENSE
apexmf-0.4.0.dist-info/METADATA
apexmf-0.4.0.dist-info/WHEEL
apexmf-0.4.0.dist-info/top_level.txt
apexmf-0.4.0.dist-info/RECORD
