Metadata-Version: 2.1
Name: apexmf
Version: 0.4.0
Summary: apexmf is a set of python modules for APEX-MODFLOW model evaluation and parameter estimation.
Download-URL: https://pypi.org/project/apexmf
Author: Seonggyu Park
Author-email: <envpsg@gmail.com>
Project-URL: Bug Tracker, https://github.com/spark-brc/apexmf/issues
Project-URL: Source Code, https://github.com/spark-brc/apexmf
Project-URL: Documentation, https://github.com/spark-brc/apexmf
Keywords: python,APEX-MODFLOW,PEST
Classifier: Development Status :: 4 - Beta
Classifier: Intended Audience :: Education
Classifier: Intended Audience :: Science/Research
Classifier: Programming Language :: Python :: 3.8
Classifier: Programming Language :: Python :: 3.9
Classifier: Programming Language :: Python :: 3.10
Classifier: Operating System :: Microsoft :: Windows
Classifier: License :: OSI Approved :: BSD License
License-File: LICENSE
Requires-Dist: pandas
Requires-Dist: numpy
Requires-Dist: pyemu
Requires-Dist: flopy
Requires-Dist: scipy
Requires-Dist: matplotlib
Requires-Dist: openpyxl
Requires-Dist: hydroeval
Requires-Dist: tqdm
Requires-Dist: termcolor
Requires-Dist: pyshp
